iocscrape/__init__.py
iocscrape/cli.py
iocscrape-0.2.1.dist-info/METADATA
iocscrape-0.2.1.dist-info/WHEEL
iocscrape-0.2.1.dist-info/entry_points.txt
iocscrape-0.2.1.dist-info/licenses/LICENSE
iocscrape-0.2.1.dist-info/RECORD
