Metadata-Version: 2.4
Name: iocscrape
Version: 0.2.1
Summary: CTI tool to extract IOCs from CTI reports (URLs or files), and write them to an output file. Low-confidence items are grouped at the end.
Author-email: Faisal Albuloushi <SQL@hotmail.co.uk>
License: The MIT License (MIT)
License-File: LICENSE
Requires-Python: >=3.10
Requires-Dist: colorama
Requires-Dist: defusedxml>=0.7.1
Requires-Dist: jaraco-context>=6.1.0
Requires-Dist: openpyxl>=3.1.5
Requires-Dist: pdfminer-six>=20251230
Requires-Dist: publicsuffix2>=2.20191221
Requires-Dist: python-docx>=1.1.2
Requires-Dist: trafilatura>=1.6.0
Requires-Dist: urllib3>=2.6.3
